LICENSE
MANIFEST.in
README.md
setup.py
examples/DisplayThread.py
examples/ReadmeExample1.py
examples/ReadmeExample2.py
src/Fourchapy/Board.py
src/Fourchapy/BoardIndex.py
src/Fourchapy/Errors.py
src/Fourchapy/Fetcher.py
src/Fourchapy/Post.py
src/Fourchapy/Thread.py
src/Fourchapy/ThreadPage.py
src/Fourchapy/__init__.py
src/python_4chapy.egg-info/PKG-INFO
src/python_4chapy.egg-info/SOURCES.txt
src/python_4chapy.egg-info/dependency_links.txt
src/python_4chapy.egg-info/requires.txt
src/python_4chapy.egg-info/top_level.txt